LICENSE
MANIFEST.in
README.md
setup.py
django_djangui.egg-info/PKG-INFO
django_djangui.egg-info/SOURCES.txt
django_djangui.egg-info/dependency_links.txt
django_djangui.egg-info/entry_points.txt
django_djangui.egg-info/pbr.json
django_djangui.egg-info/requires.txt
django_djangui.egg-info/top_level.txt
djangui/__init__.py
djangui/admin.py
djangui/apps.py
djangui/django_compat.py
djangui/djanguistorage.py
djangui/settings.py
djangui/signals.py
djangui/tasks.py
djangui/test_settings.py
djangui/test_urls.py
djangui/tests.py
djangui/urls.py
djangui/version.py
djangui/backend/__init__.py
djangui/backend/argparse_specs.py
djangui/backend/command_line.py
djangui/backend/utils.py
djangui/backend/ast/__init__.py
djangui/backend/ast/codegen.py
djangui/backend/ast/source_parser.py
djangui/conf/__init__.py
djangui/conf/project_template/__init__.py
djangui/conf/project_template/djangui_celery_app.py
djangui/conf/project_template/middleware.py
djangui/conf/project_template/requirements.txt
djangui/conf/project_template/settings/__init__.py
djangui/conf/project_template/settings/djangui_settings.py
djangui/conf/project_template/settings/user_settings.py
djangui/conf/project_template/urls/__init__.py
djangui/conf/project_template/urls/djangui_urls.py
djangui/conf/project_template/urls/user_urls.py
djangui/forms/__init__.py
djangui/forms/factory.py
djangui/forms/fields.py
djangui/forms/scripts.py
djangui/management/__init__.py
djangui/management/commands/__init__.py
djangui/management/commands/addscript.py
djangui/migrations/0001_initial.py
djangui/migrations/0002_remove_scriptparameter_output_path.py
djangui/migrations/0003_populate_from_slug.py
djangui/migrations/__init__.py
djangui/models/__init__.py
djangui/models/core.py
djangui/models/fields.py
djangui/models/mixins.py
djangui/static/djangui/djangui_logo.png
djangui/templates/djangui/base.html
djangui/templates/djangui/djangui_home.html
djangui/templates/djangui/modals/base_modal.html
djangui/templates/djangui/modals/resubmit_modal.html
djangui/templates/djangui/profile/profile_base.html
djangui/templates/djangui/registration/login.html
djangui/templates/djangui/registration/login_header.html
djangui/templates/djangui/registration/register.html
